news_signals/__init__.py
news_signals/anomaly_detection.py
news_signals/aql_builder.py
news_signals/cli.py
news_signals/data.py
news_signals/dataset_transformations.py
news_signals/exogenous_signals.py
news_signals/generate_dataset.py
news_signals/log.py
news_signals/newsapi.py
news_signals/plotting.py
news_signals/representative_story.py
news_signals/semantic_filters.py
news_signals/signals.py
news_signals/signals_dataset.py
news_signals/summarization.py
news_signals/technical_indicators.py
news_signals/test_anomaly_detection.py
news_signals/test_aql_builder.py
news_signals/test_data.py
news_signals/test_dataset_transformations.py
news_signals/test_exogenous_signals.py
news_signals/test_newsapi.py
news_signals/test_representative_story.py
news_signals/test_semantic_filters.py
news_signals/test_signals.py
news_signals/test_signals_dataset.py
news_signals/test_summarization.py
news_signals/test_yfinance_utils.py
news_signals/transform_dataset.py
news_signals/users.py
news_signals/wikidata_utils.py
news_signals/yfinance_utils.py
news_signals-0.8.2.data/data/LICENSE
news_signals-0.8.2.data/data/README.md
news_signals-0.8.2.data/data/VERSION
news_signals-0.8.2.dist-info/licenses/LICENSE
news_signals-0.8.2.dist-info/METADATA
news_signals-0.8.2.dist-info/WHEEL
news_signals-0.8.2.dist-info/entry_points.txt
news_signals-0.8.2.dist-info/top_level.txt
news_signals-0.8.2.dist-info/RECORD
