Metadata-Version: 2.4
Name: news-signals
Version: 0.8.2
Summary: A library for working with text and timeseries data.
License-File: LICENSE
Requires-Dist: appdirs>=1.4.4
Requires-Dist: arrow>=1.1.1
Requires-Dist: gdown>=4.6.4
Requires-Dist: google-cloud-storage>=2.10.0
Requires-Dist: matplotlib>=3.5.3
Requires-Dist: networkx<=2.7
Requires-Dist: numpy==1.26.4
Requires-Dist: pandas>=1.4.1
Requires-Dist: pyarrow>=11.0.0
Requires-Dist: ratelimit>=2.2.1
Requires-Dist: requests>=2.28.1
Requires-Dist: scikit-learn>=1.1.0
Requires-Dist: scipy>=1.8
Requires-Dist: spacy==3.5.4
Requires-Dist: sqlitedict>=1.7.0
Requires-Dist: tqdm>=4.62.3
Requires-Dist: Wikidata>=0.7.0
Dynamic: description
Dynamic: description-content-type
Dynamic: license-file
Dynamic: requires-dist
Dynamic: summary
